semantic_html/__init__.py
semantic_html/models.py
semantic_html/parser.py
semantic_html/utils.py
semantic_html-0.5.3.dist-info/licenses/LICENSE
semantic_html-0.5.3.dist-info/METADATA
semantic_html-0.5.3.dist-info/WHEEL
semantic_html-0.5.3.dist-info/top_level.txt
semantic_html-0.5.3.dist-info/RECORD
