Metadata-Version: 2.4
Name: semantic_html
Version: 0.5.3
Summary: Parse HTML Notes into RDF-compatible JSON-LD structures via custom mapping.
Author-email: Christoph Sander <c-sander@heimat.de>
Requires-Python: >=3.8
License-File: LICENSE
Requires-Dist: lxml==5.1.0
Requires-Dist: beautifulsoup4==4.12.2
Dynamic: license-file
